ckanext_datagovtheme-0.4.4-py3.12-nspkg.pth
ckanext/datagovtheme/__init__.py
ckanext/datagovtheme/blueprint.py
ckanext/datagovtheme/helpers.py
ckanext/datagovtheme/plugin.py
ckanext/datagovtheme/data/README.md
ckanext/datagovtheme/data/__init__.py
ckanext/datagovtheme/data/omb_bureau_codes.csv
ckanext/datagovtheme/data/dynamic_menu/__init__.py
ckanext/datagovtheme/data/dynamic_menu/logos/bureau-sample.csv
ckanext/datagovtheme/fanstatic_library/qa.js
ckanext/datagovtheme/fanstatic_library/webassets.yml
ckanext/datagovtheme/fanstatic_library/images/alpha.png
ckanext/datagovtheme/fanstatic_library/images/alpha_down.png
ckanext/datagovtheme/fanstatic_library/images/alpha_up.png
ckanext/datagovtheme/fanstatic_library/images/banner.jpg
ckanext/datagovtheme/fanstatic_library/images/breadcrumb-slash-ie7.png
ckanext/datagovtheme/fanstatic_library/images/collection.png
ckanext/datagovtheme/fanstatic_library/images/favicon.ico
ckanext/datagovtheme/fanstatic_library/images/geo-icon.png
ckanext/datagovtheme/fanstatic_library/images/header-line.png
ckanext/datagovtheme/fanstatic_library/images/header-nav-bg.png
ckanext/datagovtheme/fanstatic_library/images/icon-login.gif
ckanext/datagovtheme/fanstatic_library/images/icon-publisher.png
ckanext/datagovtheme/fanstatic_library/images/logo.png
ckanext/datagovtheme/fanstatic_library/images/logo.svg
ckanext/datagovtheme/fanstatic_library/images/number.png
ckanext/datagovtheme/fanstatic_library/images/number_down.png
ckanext/datagovtheme/fanstatic_library/images/number_up.png
ckanext/datagovtheme/fanstatic_library/images/pencil.png
ckanext/datagovtheme/fanstatic_library/images/powered-by.png
ckanext/datagovtheme/fanstatic_library/images/publisher.png
ckanext/datagovtheme/fanstatic_library/images/logos/000-00.png
ckanext/datagovtheme/fanstatic_library/images/logos/001-05.png
ckanext/datagovtheme/fanstatic_library/images/logos/001-10.png
ckanext/datagovtheme/fanstatic_library/images/logos/001-11.png
ckanext_datagovtheme-0.4.4.dist-info/METADATA
ckanext_datagovtheme-0.4.4.dist-info/WHEEL
ckanext_datagovtheme-0.4.4.dist-info/entry_points.txt
ckanext_datagovtheme-0.4.4.dist-info/namespace_packages.txt
ckanext_datagovtheme-0.4.4.dist-info/top_level.txt
ckanext_datagovtheme-0.4.4.dist-info/RECORD
