Metadata-Version: 2.4
Name: ckanext-datagovtheme
Version: 0.4.4
Summary: CKAN Extension to manage data.gov theme
Home-page: https://github.com/GSA/ckanext-datagovtheme/
Author: Data.gov
Author-email: datagovhelp@gsa.gov
License: Public Domain
Classifier: Programming Language :: Python :: 3
Dynamic: author
Dynamic: author-email
Dynamic: classifier
Dynamic: description
Dynamic: home-page
Dynamic: keywords
Dynamic: license
Dynamic: summary
